DStore-0.1.2.dist-info/DESCRIPTION.rst
DStore-0.1.2.dist-info/METADATA
DStore-0.1.2.dist-info/RECORD
DStore-0.1.2.dist-info/WHEEL
DStore-0.1.2.dist-info/metadata.json
DStore-0.1.2.dist-info/top_level.txt
dstore/Error.py
dstore/Event.py
dstore/MemoryStore.py
dstore/Model.py
dstore/Store.py
dstore/__init__.py
dstore/mod.py
dstore/var.py
