Metadata-Version: 2.0
Name: DStore
Version: 0.1.2
Summary: Python Data abstraction layer (ORM)
Home-page: https://github.com/MarkLark/dstore
Author: Mark Pittaway
Author-email: mark.pittaway@mlit.net.au
License: MIT
Platform: any
Classifier: Development Status :: 3 - Alpha
Classifier: Intended Audience :: Developers
Classifier: License :: OSI Approved :: MIT License
Classifier: Operating System :: OS Independent
Classifier: Programming Language :: Python
Classifier: Programming Language :: Python :: 2.6
Classifier: Programming Language :: Python :: 2.7
Classifier: Programming Language :: Python :: 3.3
Classifier: Programming Language :: Python :: 3.4
Classifier: Programming Language :: Python :: 3.5
Classifier: Programming Language :: Python :: 3.6
Classifier: Topic :: Database :: Front-Ends
Requires-Dist: tabulate
